pydqkit/__about__.py
pydqkit/__init__.py
pydqkit/core.py
pydqkit/profiling.py
pydqkit/viz.py
pydqkit-0.0.1.dist-info/METADATA
pydqkit-0.0.1.dist-info/WHEEL
pydqkit-0.0.1.dist-info/licenses/LICENSE
pydqkit-0.0.1.dist-info/RECORD
