Metadata-Version: 2.4
Name: pydqkit
Version: 0.0.1
Summary: A developer-first Python toolkit for data quality profiling, validation, and interactive HTML reports.
Project-URL: Documentation, https://github.com/Niki9001/pydqkit#readme
Project-URL: Issues, https://github.com/Niki9001/pydqkit/issues
Project-URL: Source, https://github.com/Niki9001/pydqkit
Author-email: Niki Zheng <nikizheng90@gmail.com>, Luqun Li <success@shnu.edu.cn>
License: MIT License
License-File: LICENSE
Keywords: data engineering,data profiling,data quality,data validation,data-engineering,data-profiling,data-quality,data-validation,etl,pandas,sanity check,sanity-check
Classifier: Development Status :: 4 - Beta
Classifier: License :: OSI Approved :: MIT License
Classifier: Operating System :: OS Independent
Classifier: Programming Language :: Python :: 3
Classifier: Programming Language :: Python :: 3.8
Classifier: Programming Language :: Python :: 3.9
Classifier: Programming Language :: Python :: 3.10
Classifier: Programming Language :: Python :: 3.11
Classifier: Programming Language :: Python :: 3.12
Requires-Python: >=3.8
Requires-Dist: pandas>=1.5
